{
  "restaurants": [
    {
      "id": 1,
      "image": "vegan-restaurant-logo-design_1438-10.png",
      "image-food": "prato-de-restaurante-vegetariano.png",
      "name": "Restaurante 1",
      "description": "Lorem Ipsum is simply dummy text of the printing and typesetting",
      "address": "Rua 1",
      "status": "Aberto Agora",
      "monday": "11:30 ás 15:00",
      "saturday": "11:30 ás 22:00",
      "sunday": "13:30 ás 15:00",
      "lunches": [
        {
          "image": "prato-de-restaurante-vegetariano.png",
          "name": "Nome do prato",
          "description": "Lorem Ipsum is simply dummy text of the printing and typesetting",
          "price": "19,90"
        },
        {
          "image": "",
          "name": "Nome do prato",
          "description": "Lorem Ipsum is simply dummy text of the printing and typesetting",
          "price": "19,90"
        },
        {
          "image": "",
          "name": "Nome do prato",
          "description": "Lorem Ipsum is simply dummy text of the printing and typesetting",
          "price": "19,90"
        },
        {
          "image": "",
          "name": "Nome do prato",
          "description": "Lorem Ipsum is simply dummy text of the printing and typesetting",
          "price": "19,90"
        }
      ],
      "drinks": [
        {
          "image": "",
          "name": "Nome da Bebida",
          "description": "Lorem Ipsum is simply dummy text of the printing and typesetting",
          "price": "15,90"
        },
        {
          "image": "",
          "name": "Nome da Bebida",
          "description": "Lorem Ipsum is simply dummy text of the printing and typesetting",
          "price": "15,90"
        },
        {
          "image": "",
          "name": "Nome da Bebida",
          "description": "Lorem Ipsum is simply dummy text of the printing and typesetting",
          "price": "15,90"
        },
        {
          "image": "",
          "name": "Nome da Bebida",
          "description": "Lorem Ipsum is simply dummy text of the printing and typesetting",
          "price": "15,90"
        }
      ],
      "desserts": [
        {
          "image": "",
          "name": "Nome da Sobremesa",
          "description": "Lorem Ipsum is simply dummy text of the printing and typesetting",
          "price": "10,90"
        },
        {
          "image": "",
          "name": "Nome da Sobremesa",
          "description": "Lorem Ipsum is simply dummy text of the printing and typesetting",
          "price": "10,90"
        },
        {
          "image": "",
          "name": "Nome da Sobremesa",
          "description": "Lorem Ipsum is simply dummy text of the printing and typesetting",
          "price": "10,90"
        },
        {
          "image": "",
          "name": "Nome da Sobremesa",
          "description": "Lorem Ipsum is simply dummy text of the printing and typesetting",
          "price": "10,90"
        }
      ]
    },
    {
      "id": 2,
      "image": "vegan-restaurant-logo-design_1438-10.png",
      "name": "Restaurante 2",
      "description": "Lorem Ipsum is simply dummy text of the printing and typesetting",
      "address": "Rua 2",
      "status": "Aberto Agora",
      "monday": "11:30 ás 15:00",
      "saturday": "11:30 ás 22:00",
      "sunday": "13:30 ás 15:00",
      "lunches": [
        {
          "image": "prato-de-restaurante-vegetariano.png",
          "name": "Nome do prato",
          "description": "Lorem Ipsum is simply dummy text of the printing and typesetting",
          "price": "19,90"
        },
        {
          "image": "",
          "name": "Nome do prato",
          "description": "Lorem Ipsum is simply dummy text of the printing and typesetting",
          "price": "19,90"
        },
        {
          "image": "",
          "name": "Nome do prato",
          "description": "Lorem Ipsum is simply dummy text of the printing and typesetting",
          "price": "19,90"
        },
        {
          "image": "",
          "name": "Nome do prato",
          "description": "Lorem Ipsum is simply dummy text of the printing and typesetting",
          "price": "19,90"
        }
      ],
      "drinks": [
        {
          "image": "",
          "name": "Nome da Bebida",
          "description": "Lorem Ipsum is simply dummy text of the printing and typesetting",
          "price": "15,90"
        },
        {
          "image": "",
          "name": "Nome da Bebida",
          "description": "Lorem Ipsum is simply dummy text of the printing and typesetting",
          "price": "15,90"
        },
        {
          "image": "",
          "name": "Nome da Bebida",
          "description": "Lorem Ipsum is simply dummy text of the printing and typesetting",
          "price": "15,90"
        },
        {
          "image": "",
          "name": "Nome da Bebida",
          "description": "Lorem Ipsum is simply dummy text of the printing and typesetting",
          "price": "15,90"
        }
      ],
      "desserts": [
        {
          "image": "",
          "name": "Nome da Sobremesa",
          "description": "Lorem Ipsum is simply dummy text of the printing and typesetting",
          "price": "10,90"
        },
        {
          "image": "",
          "name": "Nome da Sobremesa",
          "description": "Lorem Ipsum is simply dummy text of the printing and typesetting",
          "price": "10,90"
        },
        {
          "image": "",
          "name": "Nome da Sobremesa",
          "description": "Lorem Ipsum is simply dummy text of the printing and typesetting",
          "price": "10,90"
        },
        {
          "image": "",
          "name": "Nome da Sobremesa",
          "description": "Lorem Ipsum is simply dummy text of the printing and typesetting",
          "price": "10,90"
        }
      ]
    },
    {
      "id": 3,
      "image": "vegan-restaurant-logo-design_1438-10.png",
      "name": "Restaurante 3",
      "description": "Lorem Ipsum is simply dummy text of the printing and typesetting",
      "address": "Rua 3",
      "status": "Aberto Agora",
      "monday": "11:30 ás 15:00",
      "saturday": "11:30 ás 22:00",
      "sunday": "13:30 ás 15:00",
      "lunches": [
        {
          "image": "prato-de-restaurante-vegetariano.png",
          "name": "Nome do prato",
          "description": "Lorem Ipsum is simply dummy text of the printing and typesetting",
          "price": "19,90"
        },
        {
          "image": "",
          "name": "Nome do prato",
          "description": "Lorem Ipsum is simply dummy text of the printing and typesetting",
          "price": "19,90"
        },
        {
          "image": "",
          "name": "Nome do prato",
          "description": "Lorem Ipsum is simply dummy text of the printing and typesetting",
          "price": "19,90"
        },
        {
          "image": "",
          "name": "Nome do prato",
          "description": "Lorem Ipsum is simply dummy text of the printing and typesetting",
          "price": "19,90"
        }
      ],
      "drinks": [
        {
          "image": "",
          "name": "Nome da Bebida",
          "description": "Lorem Ipsum is simply dummy text of the printing and typesetting",
          "price": "15,90"
        },
        {
          "image": "",
          "name": "Nome da Bebida",
          "description": "Lorem Ipsum is simply dummy text of the printing and typesetting",
          "price": "15,90"
        },
        {
          "image": "",
          "name": "Nome da Bebida",
          "description": "Lorem Ipsum is simply dummy text of the printing and typesetting",
          "price": "15,90"
        },
        {
          "image": "",
          "name": "Nome da Bebida",
          "description": "Lorem Ipsum is simply dummy text of the printing and typesetting",
          "price": "15,90"
        }
      ],
      "desserts": [
        {
          "image": "",
          "name": "Nome da Sobremesa",
          "description": "Lorem Ipsum is simply dummy text of the printing and typesetting",
          "price": "10,90"
        },
        {
          "image": "",
          "name": "Nome da Sobremesa",
          "description": "Lorem Ipsum is simply dummy text of the printing and typesetting",
          "price": "10,90"
        },
        {
          "image": "",
          "name": "Nome da Sobremesa",
          "description": "Lorem Ipsum is simply dummy text of the printing and typesetting",
          "price": "10,90"
        },
        {
          "image": "",
          "name": "Nome da Sobremesa",
          "description": "Lorem Ipsum is simply dummy text of the printing and typesetting",
          "price": "10,90"
        }
      ]
    },
    {
      "id": 4,
      "image": "vegan-restaurant-logo-design_1438-10.png",
      "name": "Restaurante 4",
      "description": "Lorem Ipsum is simply dummy text of the printing and typesetting",
      "address": "Rua 4",
      "status": "Fechado Agora",
      "monday": "11:30 ás 15:00",
      "saturday": "11:30 ás 22:00",
      "sunday": "13:30 ás 15:00",
      "lunches": [
        {
          "image": "prato-de-restaurante-vegetariano.png",
          "name": "Nome do prato",
          "description": "Lorem Ipsum is simply dummy text of the printing and typesetting",
          "price": "19,90"
        },
        {
          "image": "",
          "name": "Nome do prato",
          "description": "Lorem Ipsum is simply dummy text of the printing and typesetting",
          "price": "19,90"
        },
        {
          "image": "",
          "name": "Nome do prato",
          "description": "Lorem Ipsum is simply dummy text of the printing and typesetting",
          "price": "19,90"
        },
        {
          "image": "",
          "name": "Nome do prato",
          "description": "Lorem Ipsum is simply dummy text of the printing and typesetting",
          "price": "19,90"
        }
      ],
      "drinks": [
        {
          "image": "",
          "name": "Nome da Bebida",
          "description": "Lorem Ipsum is simply dummy text of the printing and typesetting",
          "price": "15,90"
        },
        {
          "image": "",
          "name": "Nome da Bebida",
          "description": "Lorem Ipsum is simply dummy text of the printing and typesetting",
          "price": "15,90"
        },
        {
          "image": "",
          "name": "Nome da Bebida",
          "description": "Lorem Ipsum is simply dummy text of the printing and typesetting",
          "price": "15,90"
        },
        {
          "image": "",
          "name": "Nome da Bebida",
          "description": "Lorem Ipsum is simply dummy text of the printing and typesetting",
          "price": "15,90"
        }
      ],
      "desserts": [
        {
          "image": "",
          "name": "Nome da Sobremesa",
          "description": "Lorem Ipsum is simply dummy text of the printing and typesetting",
          "price": "10,90"
        },
        {
          "image": "",
          "name": "Nome da Sobremesa",
          "description": "Lorem Ipsum is simply dummy text of the printing and typesetting",
          "price": "10,90"
        },
        {
          "image": "",
          "name": "Nome da Sobremesa",
          "description": "Lorem Ipsum is simply dummy text of the printing and typesetting",
          "price": "10,90"
        },
        {
          "image": "",
          "name": "Nome da Sobremesa",
          "description": "Lorem Ipsum is simply dummy text of the printing and typesetting",
          "price": "10,90"
        }
      ]
    },
    {
      "id": 5,
      "image": "vegan-restaurant-logo-design_1438-10.png",
      "name": "Restaurante 5",
      "description": "Lorem Ipsum is simply dummy text of the printing and typesetting",
      "address": "Rua 5",
      "status": "Aberto Agora",
      "monday": "11:30 ás 15:00",
      "saturday": "11:30 ás 22:00",
      "sunday": "13:30 ás 15:00",
      "lunches": [
        {
          "image": "prato-de-restaurante-vegetariano.png",
          "name": "Nome do prato",
          "description": "Lorem Ipsum is simply dummy text of the printing and typesetting",
          "price": "19,90"
        },
        {
          "image": "",
          "name": "Nome do prato",
          "description": "Lorem Ipsum is simply dummy text of the printing and typesetting",
          "price": "19,90"
        },
        {
          "image": "",
          "name": "Nome do prato",
          "description": "Lorem Ipsum is simply dummy text of the printing and typesetting",
          "price": "19,90"
        },
        {
          "image": "",
          "name": "Nome do prato",
          "description": "Lorem Ipsum is simply dummy text of the printing and typesetting",
          "price": "19,90"
        }
      ],
      "drinks": [
        {
          "image": "",
          "name": "Nome da Bebida",
          "description": "Lorem Ipsum is simply dummy text of the printing and typesetting",
          "price": "15,90"
        },
        {
          "image": "",
          "name": "Nome da Bebida",
          "description": "Lorem Ipsum is simply dummy text of the printing and typesetting",
          "price": "15,90"
        },
        {
          "image": "",
          "name": "Nome da Bebida",
          "description": "Lorem Ipsum is simply dummy text of the printing and typesetting",
          "price": "15,90"
        },
        {
          "image": "",
          "name": "Nome da Bebida",
          "description": "Lorem Ipsum is simply dummy text of the printing and typesetting",
          "price": "15,90"
        }
      ],
      "desserts": [
        {
          "image": "",
          "name": "Nome da Sobremesa",
          "description": "Lorem Ipsum is simply dummy text of the printing and typesetting",
          "price": "10,90"
        },
        {
          "image": "",
          "name": "Nome da Sobremesa",
          "description": "Lorem Ipsum is simply dummy text of the printing and typesetting",
          "price": "10,90"
        },
        {
          "image": "",
          "name": "Nome da Sobremesa",
          "description": "Lorem Ipsum is simply dummy text of the printing and typesetting",
          "price": "10,90"
        },
        {
          "image": "",
          "name": "Nome da Sobremesa",
          "description": "Lorem Ipsum is simply dummy text of the printing and typesetting",
          "price": "10,90"
        }
      ]
    },
    {
      "id": 6,
      "image": "vegan-restaurant-logo-design_1438-10.png",
      "name": "Restaurante 6",
      "description": "Lorem Ipsum is simply dummy text of the printing and typesetting",
      "address": "Rua 6",
      "status": "Fechado Agora",
      "monday": "11:30 ás 15:00",
      "saturday": "11:30 ás 22:00",
      "sunday": "13:30 ás 15:00",
      "lunches": [
        {
          "image": "prato-de-restaurante-vegetariano.png",
          "name": "Nome do prato",
          "description": "Lorem Ipsum is simply dummy text of the printing and typesetting",
          "price": "19,90"
        },
        {
          "image": "",
          "name": "Nome do prato",
          "description": "Lorem Ipsum is simply dummy text of the printing and typesetting",
          "price": "19,90"
        },
        {
          "image": "",
          "name": "Nome do prato",
          "description": "Lorem Ipsum is simply dummy text of the printing and typesetting",
          "price": "19,90"
        },
        {
          "image": "",
          "name": "Nome do prato",
          "description": "Lorem Ipsum is simply dummy text of the printing and typesetting",
          "price": "19,90"
        }
      ],
      "drinks": [
        {
          "image": "",
          "name": "Nome da Bebida",
          "description": "Lorem Ipsum is simply dummy text of the printing and typesetting",
          "price": "15,90"
        },
        {
          "image": "",
          "name": "Nome da Bebida",
          "description": "Lorem Ipsum is simply dummy text of the printing and typesetting",
          "price": "15,90"
        },
        {
          "image": "",
          "name": "Nome da Bebida",
          "description": "Lorem Ipsum is simply dummy text of the printing and typesetting",
          "price": "15,90"
        },
        {
          "image": "",
          "name": "Nome da Bebida",
          "description": "Lorem Ipsum is simply dummy text of the printing and typesetting",
          "price": "15,90"
        }
      ],
      "desserts": [
        {
          "image": "",
          "name": "Nome da Sobremesa",
          "description": "Lorem Ipsum is simply dummy text of the printing and typesetting",
          "price": "10,90"
        },
        {
          "image": "",
          "name": "Nome da Sobremesa",
          "description": "Lorem Ipsum is simply dummy text of the printing and typesetting",
          "price": "10,90"
        },
        {
          "image": "",
          "name": "Nome da Sobremesa",
          "description": "Lorem Ipsum is simply dummy text of the printing and typesetting",
          "price": "10,90"
        },
        {
          "image": "",
          "name": "Nome da Sobremesa",
          "description": "Lorem Ipsum is simply dummy text of the printing and typesetting",
          "price": "10,90"
        }
      ]
    },
    {
      "id": 7,
      "image": "vegan-restaurant-logo-design_1438-10.png",
      "name": "Restaurante 7",
      "description": "Lorem Ipsum is simply dummy text of the printing and typesetting",
      "address": "Rua 7",
      "status": "Fechado Agora",
      "monday": "11:30 ás 15:00",
      "saturday": "11:30 ás 22:00",
      "sunday": "13:30 ás 15:00",
      "lunches": [
        {
          "image": "prato-de-restaurante-vegetariano.png",
          "name": "Nome do prato",
          "description": "Lorem Ipsum is simply dummy text of the printing and typesetting",
          "price": "19,90"
        },
        {
          "image": "",
          "name": "Nome do prato",
          "description": "Lorem Ipsum is simply dummy text of the printing and typesetting",
          "price": "19,90"
        },
        {
          "image": "",
          "name": "Nome do prato",
          "description": "Lorem Ipsum is simply dummy text of the printing and typesetting",
          "price": "19,90"
        },
        {
          "image": "",
          "name": "Nome do prato",
          "description": "Lorem Ipsum is simply dummy text of the printing and typesetting",
          "price": "19,90"
        }
      ],
      "drinks": [
        {
          "image": "",
          "name": "Nome da Bebida",
          "description": "Lorem Ipsum is simply dummy text of the printing and typesetting",
          "price": "15,90"
        },
        {
          "image": "",
          "name": "Nome da Bebida",
          "description": "Lorem Ipsum is simply dummy text of the printing and typesetting",
          "price": "15,90"
        },
        {
          "image": "",
          "name": "Nome da Bebida",
          "description": "Lorem Ipsum is simply dummy text of the printing and typesetting",
          "price": "15,90"
        },
        {
          "image": "",
          "name": "Nome da Bebida",
          "description": "Lorem Ipsum is simply dummy text of the printing and typesetting",
          "price": "15,90"
        }
      ],
      "desserts": [
        {
          "image": "",
          "name": "Nome da Sobremesa",
          "description": "Lorem Ipsum is simply dummy text of the printing and typesetting",
          "price": "10,90"
        },
        {
          "image": "",
          "name": "Nome da Sobremesa",
          "description": "Lorem Ipsum is simply dummy text of the printing and typesetting",
          "price": "10,90"
        },
        {
          "image": "",
          "name": "Nome da Sobremesa",
          "description": "Lorem Ipsum is simply dummy text of the printing and typesetting",
          "price": "10,90"
        },
        {
          "image": "",
          "name": "Nome da Sobremesa",
          "description": "Lorem Ipsum is simply dummy text of the printing and typesetting",
          "price": "10,90"
        }
      ]
    },
    {
      "id": 8,
      "image": "vegan-restaurant-logo-design_1438-10.png",
      "name": "Restaurante 8",
      "description": "Lorem Ipsum is simply dummy text of the printing and typesetting",
      "address": "Rua 8",
      "status": "Fechado Agora",
      "monday": "11:30 ás 15:00",
      "saturday": "11:30 ás 22:00",
      "sunday": "13:30 ás 15:00",
      "lunches": [
        {
          "image": "prato-de-restaurante-vegetariano.png",
          "name": "Nome do prato",
          "description": "Lorem Ipsum is simply dummy text of the printing and typesetting",
          "price": "19,90"
        },
        {
          "image": "",
          "name": "Nome do prato",
          "description": "Lorem Ipsum is simply dummy text of the printing and typesetting",
          "price": "19,90"
        },
        {
          "image": "",
          "name": "Nome do prato",
          "description": "Lorem Ipsum is simply dummy text of the printing and typesetting",
          "price": "19,90"
        },
        {
          "image": "",
          "name": "Nome do prato",
          "description": "Lorem Ipsum is simply dummy text of the printing and typesetting",
          "price": "19,90"
        }
      ],
      "drinks": [
        {
          "image": "",
          "name": "Nome da Bebida",
          "description": "Lorem Ipsum is simply dummy text of the printing and typesetting",
          "price": "15,90"
        },
        {
          "image": "",
          "name": "Nome da Bebida",
          "description": "Lorem Ipsum is simply dummy text of the printing and typesetting",
          "price": "15,90"
        },
        {
          "image": "",
          "name": "Nome da Bebida",
          "description": "Lorem Ipsum is simply dummy text of the printing and typesetting",
          "price": "15,90"
        },
        {
          "image": "",
          "name": "Nome da Bebida",
          "description": "Lorem Ipsum is simply dummy text of the printing and typesetting",
          "price": "15,90"
        }
      ],
      "desserts": [
        {
          "image": "",
          "name": "Nome da Sobremesa",
          "description": "Lorem Ipsum is simply dummy text of the printing and typesetting",
          "price": "10,90"
        },
        {
          "image": "",
          "name": "Nome da Sobremesa",
          "description": "Lorem Ipsum is simply dummy text of the printing and typesetting",
          "price": "10,90"
        },
        {
          "image": "",
          "name": "Nome da Sobremesa",
          "description": "Lorem Ipsum is simply dummy text of the printing and typesetting",
          "price": "10,90"
        },
        {
          "image": "",
          "name": "Nome da Sobremesa",
          "description": "Lorem Ipsum is simply dummy text of the printing and typesetting",
          "price": "10,90"
        }
      ]
    },
    {
      "id": 9,
      "image": "vegan-restaurant-logo-design_1438-10.png",
      "name": "Restaurante 9",
      "description": "Lorem Ipsum is simply dummy text of the printing and typesetting",
      "address": "Rua 9",
      "status": "Aberto Agora",
      "monday": "11:30 ás 15:00",
      "saturday": "11:30 ás 22:00",
      "sunday": "13:30 ás 15:00",
      "lunches": [
        {
          "image": "prato-de-restaurante-vegetariano.png",
          "name": "Nome do prato",
          "description": "Lorem Ipsum is simply dummy text of the printing and typesetting",
          "price": "19,90"
        },
        {
          "image": "",
          "name": "Nome do prato",
          "description": "Lorem Ipsum is simply dummy text of the printing and typesetting",
          "price": "19,90"
        },
        {
          "image": "",
          "name": "Nome do prato",
          "description": "Lorem Ipsum is simply dummy text of the printing and typesetting",
          "price": "19,90"
        },
        {
          "image": "",
          "name": "Nome do prato",
          "description": "Lorem Ipsum is simply dummy text of the printing and typesetting",
          "price": "19,90"
        }
      ],
      "drinks": [
        {
          "image": "",
          "name": "Nome da Bebida",
          "description": "Lorem Ipsum is simply dummy text of the printing and typesetting",
          "price": "15,90"
        },
        {
          "image": "",
          "name": "Nome da Bebida",
          "description": "Lorem Ipsum is simply dummy text of the printing and typesetting",
          "price": "15,90"
        },
        {
          "image": "",
          "name": "Nome da Bebida",
          "description": "Lorem Ipsum is simply dummy text of the printing and typesetting",
          "price": "15,90"
        },
        {
          "image": "",
          "name": "Nome da Bebida",
          "description": "Lorem Ipsum is simply dummy text of the printing and typesetting",
          "price": "15,90"
        }
      ],
      "desserts": [
        {
          "image": "",
          "name": "Nome da Sobremesa",
          "description": "Lorem Ipsum is simply dummy text of the printing and typesetting",
          "price": "10,90"
        },
        {
          "image": "",
          "name": "Nome da Sobremesa",
          "description": "Lorem Ipsum is simply dummy text of the printing and typesetting",
          "price": "10,90"
        },
        {
          "image": "",
          "name": "Nome da Sobremesa",
          "description": "Lorem Ipsum is simply dummy text of the printing and typesetting",
          "price": "10,90"
        },
        {
          "image": "",
          "name": "Nome da Sobremesa",
          "description": "Lorem Ipsum is simply dummy text of the printing and typesetting",
          "price": "10,90"
        }
      ]
    },
    {
      "id": 10,
      "image": "vegan-restaurant-logo-design_1438-10.png",
      "name": "Restaurante 10",
      "description": "Lorem Ipsum is simply dummy text of the printing and typesetting",
      "address": "Rua 10",
      "status": "Aberto Agora",
      "monday": "11:30 ás 15:00",
      "saturday": "11:30 ás 22:00",
      "sunday": "13:30 ás 15:00",
      "lunches": [
        {
          "image": "prato-de-restaurante-vegetariano.png",
          "name": "Nome do prato",
          "description": "Lorem Ipsum is simply dummy text of the printing and typesetting",
          "price": "19,90"
        },
        {
          "image": "",
          "name": "Nome do prato",
          "description": "Lorem Ipsum is simply dummy text of the printing and typesetting",
          "price": "19,90"
        },
        {
          "image": "",
          "name": "Nome do prato",
          "description": "Lorem Ipsum is simply dummy text of the printing and typesetting",
          "price": "19,90"
        },
        {
          "image": "",
          "name": "Nome do prato",
          "description": "Lorem Ipsum is simply dummy text of the printing and typesetting",
          "price": "19,90"
        }
      ],
      "drinks": [
        {
          "image": "",
          "name": "Nome da Bebida",
          "description": "Lorem Ipsum is simply dummy text of the printing and typesetting",
          "price": "15,90"
        },
        {
          "image": "",
          "name": "Nome da Bebida",
          "description": "Lorem Ipsum is simply dummy text of the printing and typesetting",
          "price": "15,90"
        },
        {
          "image": "",
          "name": "Nome da Bebida",
          "description": "Lorem Ipsum is simply dummy text of the printing and typesetting",
          "price": "15,90"
        },
        {
          "image": "",
          "name": "Nome da Bebida",
          "description": "Lorem Ipsum is simply dummy text of the printing and typesetting",
          "price": "15,90"
        }
      ],
      "desserts": [
        {
          "image": "",
          "name": "Nome da Sobremesa",
          "description": "Lorem Ipsum is simply dummy text of the printing and typesetting",
          "price": "10,90"
        },
        {
          "image": "",
          "name": "Nome da Sobremesa",
          "description": "Lorem Ipsum is simply dummy text of the printing and typesetting",
          "price": "10,90"
        },
        {
          "image": "",
          "name": "Nome da Sobremesa",
          "description": "Lorem Ipsum is simply dummy text of the printing and typesetting",
          "price": "10,90"
        },
        {
          "image": "",
          "name": "Nome da Sobremesa",
          "description": "Lorem Ipsum is simply dummy text of the printing and typesetting",
          "price": "10,90"
        }
      ]
    },
    {
      "id": 11,
      "image": "vegan-restaurant-logo-design_1438-10.png",
      "name": "Restaurante 11",
      "description": "Lorem Ipsum is simply dummy text of the printing and typesetting",
      "address": "Rua 11",
      "status": "Fechado Agora",
      "monday": "11:30 ás 15:00",
      "saturday": "11:30 ás 22:00",
      "sunday": "13:30 ás 15:00",
      "lunches": [
        {
          "image": "prato-de-restaurante-vegetariano.png",
          "name": "Nome do prato",
          "description": "Lorem Ipsum is simply dummy text of the printing and typesetting",
          "price": "19,90"
        },
        {
          "image": "",
          "name": "Nome do prato",
          "description": "Lorem Ipsum is simply dummy text of the printing and typesetting",
          "price": "19,90"
        },
        {
          "image": "",
          "name": "Nome do prato",
          "description": "Lorem Ipsum is simply dummy text of the printing and typesetting",
          "price": "19,90"
        },
        {
          "image": "",
          "name": "Nome do prato",
          "description": "Lorem Ipsum is simply dummy text of the printing and typesetting",
          "price": "19,90"
        }
      ],
      "drinks": [
        {
          "image": "",
          "name": "Nome da Bebida",
          "description": "Lorem Ipsum is simply dummy text of the printing and typesetting",
          "price": "15,90"
        },
        {
          "image": "",
          "name": "Nome da Bebida",
          "description": "Lorem Ipsum is simply dummy text of the printing and typesetting",
          "price": "15,90"
        },
        {
          "image": "",
          "name": "Nome da Bebida",
          "description": "Lorem Ipsum is simply dummy text of the printing and typesetting",
          "price": "15,90"
        },
        {
          "image": "",
          "name": "Nome da Bebida",
          "description": "Lorem Ipsum is simply dummy text of the printing and typesetting",
          "price": "15,90"
        }
      ],
      "desserts": [
        {
          "image": "",
          "name": "Nome da Sobremesa",
          "description": "Lorem Ipsum is simply dummy text of the printing and typesetting",
          "price": "10,90"
        },
        {
          "image": "",
          "name": "Nome da Sobremesa",
          "description": "Lorem Ipsum is simply dummy text of the printing and typesetting",
          "price": "10,90"
        },
        {
          "image": "",
          "name": "Nome da Sobremesa",
          "description": "Lorem Ipsum is simply dummy text of the printing and typesetting",
          "price": "10,90"
        },
        {
          "image": "",
          "name": "Nome da Sobremesa",
          "description": "Lorem Ipsum is simply dummy text of the printing and typesetting",
          "price": "10,90"
        }
      ]
    },
    {
      "id": 12,
      "image": "vegan-restaurant-logo-design_1438-10.png",
      "name": "Restaurante 12",
      "description": "Lorem Ipsum is simply dummy text of the printing and typesetting",
      "address": "Rua 12",
      "status": "Fechado Agora",
      "monday": "11:30 ás 15:00",
      "saturday": "11:30 ás 22:00",
      "sunday": "13:30 ás 15:00",
      "lunches": [
        {
          "image": "prato-de-restaurante-vegetariano.png",
          "name": "Nome do prato",
          "description": "Lorem Ipsum is simply dummy text of the printing and typesetting",
          "price": "19,90"
        },
        {
          "image": "",
          "name": "Nome do prato",
          "description": "Lorem Ipsum is simply dummy text of the printing and typesetting",
          "price": "19,90"
        },
        {
          "image": "",
          "name": "Nome do prato",
          "description": "Lorem Ipsum is simply dummy text of the printing and typesetting",
          "price": "19,90"
        },
        {
          "image": "",
          "name": "Nome do prato",
          "description": "Lorem Ipsum is simply dummy text of the printing and typesetting",
          "price": "19,90"
        }
      ],
      "drinks": [
        {
          "image": "",
          "name": "Nome da Bebida",
          "description": "Lorem Ipsum is simply dummy text of the printing and typesetting",
          "price": "15,90"
        },
        {
          "image": "",
          "name": "Nome da Bebida",
          "description": "Lorem Ipsum is simply dummy text of the printing and typesetting",
          "price": "15,90"
        },
        {
          "image": "",
          "name": "Nome da Bebida",
          "description": "Lorem Ipsum is simply dummy text of the printing and typesetting",
          "price": "15,90"
        },
        {
          "image": "",
          "name": "Nome da Bebida",
          "description": "Lorem Ipsum is simply dummy text of the printing and typesetting",
          "price": "15,90"
        }
      ],
      "desserts": [
        {
          "image": "",
          "name": "Nome da Sobremesa",
          "description": "Lorem Ipsum is simply dummy text of the printing and typesetting",
          "price": "10,90"
        },
        {
          "image": "",
          "name": "Nome da Sobremesa",
          "description": "Lorem Ipsum is simply dummy text of the printing and typesetting",
          "price": "10,90"
        },
        {
          "image": "",
          "name": "Nome da Sobremesa",
          "description": "Lorem Ipsum is simply dummy text of the printing and typesetting",
          "price": "10,90"
        },
        {
          "image": "",
          "name": "Nome da Sobremesa",
          "description": "Lorem Ipsum is simply dummy text of the printing and typesetting",
          "price": "10,90"
        }
      ]
    }
  ]
}